youtubesearchpython/__init__.py
youtubesearchpython/extras.py
youtubesearchpython/search.py
youtubesearchpython/streamurlfetcher.py
youtubesearchpython/__future__/__init__.py
youtubesearchpython/__future__/extras.py
youtubesearchpython/__future__/search.py
youtubesearchpython/__future__/streamurlfetcher.py
youtubesearchpython/core/__init__.py
youtubesearchpython/core/channel.py
youtubesearchpython/core/channelsearch.py
youtubesearchpython/core/comments.py
youtubesearchpython/core/componenthandler.py
youtubesearchpython/core/constants.py
youtubesearchpython/core/hashtag.py
youtubesearchpython/core/playlist.py
youtubesearchpython/core/requests.py
youtubesearchpython/core/search.py
youtubesearchpython/core/streamurlfetcher.py
youtubesearchpython/core/suggestions.py
youtubesearchpython/core/transcript.py
youtubesearchpython/core/utils.py
youtubesearchpython/core/video.py
youtubesearchpython/handlers/componenthandler.py
youtubesearchpython/handlers/requesthandler.py
youtubesearchpython/legacy/__init__.py
youtube_search_python-1.6.6.dist-info/LICENSE
youtube_search_python-1.6.6.dist-info/METADATA
youtube_search_python-1.6.6.dist-info/WHEEL
youtube_search_python-1.6.6.dist-info/top_level.txt
youtube_search_python-1.6.6.dist-info/RECORD
