Metadata-Version: 2.1
Name: youtube-search-python
Version: 1.6.6
Summary: Search for YouTube videos, channels & playlists & get video information using link WITHOUT YouTube Data API v3
Home-page: https://github.com/alexmercerind/youtube-search-python
Author: Hitesh Kumar Saini
Author-email: saini123hitesh@gmail.com
License: MIT
Platform: UNKNOWN
Classifier: Programming Language :: Python :: 3
Classifier: License :: OSI Approved :: MIT License
Classifier: Operating System :: OS Independent
Requires-Python: >=3.6
License-File: LICENSE
